{
  "slug": "public-wifi",
  "unit": "Unit 10: Online Safety and Security",
  "module": "Online Transactions",
  "order": 1070,
  "title": "Public WiFi Safety",
  "videoUrl": "",
  "drDigitalIntro": "Public WiFi is convenient but less secure than home.\n\u2022 Others on the network could see your data.\n\u2022 Avoid banking or email on it; stick to https sites.\n\u2022 A VPN adds protection. Reading the news is fine \u2014 just skip anything private.",
  "playgroundTask": {
    "type": "guided-security",
    "goal": "You identified risks on public WiFi",
    "steps": [
      {
        "say": "Inspect 'Free WiFi Login' \u2014 this link is from a suspicious sign-in portal.",
        "action": "inspect-link",
        "target": "Free WiFi Login"
      },
      {
        "say": "The URL is unsecured. Mark it Dangerous.",
        "action": "mark-dangerous",
        "target": "Free WiFi Login"
      },
      {
        "say": "Now go to Privacy and turn off Location when on public networks.",
        "action": "go-to-section",
        "target": "privacy"
      },
      {
        "say": "Toggle off Location sharing.",
        "action": "toggle-setting",
        "target": "Location"
      }
    ]
  },
  "drDigitalSuccess": "You identified public WiFi risks! Be cautious about what you access on public networks.",
  "drDigitalHint": "Inspect links for unsecured URLs and limit what personal info your device shares on public networks."
}
